cututil/__init__.py
cututil/cututil.py
cututil-0.0.8.dist-info/LICENSE
cututil-0.0.8.dist-info/METADATA
cututil-0.0.8.dist-info/WHEEL
cututil-0.0.8.dist-info/top_level.txt
cututil-0.0.8.dist-info/RECORD
